{
  "episodeId": "ep1",
  "start": "intro",
  "nodes": {
    "intro": {
      "title": "Tavern",
      "text": "You step into an old tavern. The smell of wet wood and candle smoke fills the air.",
      "choices": [
        { "label": "Begin the adventure", "next": "choose_class" }
      ]
    },
    "choose_class": {
      "title": "Prologue",
      "text": "Before everything changes, you must choose your path.",
      "ui": { "type": "class_select" }
    },
    "after_class": {
      "title": "Tavern",
      "text": "Your choice feels final. Tonight, hesitation will not be forgiven.",
      "choices": [
        { "label": "Step into the back alley", "next": "alley" }
      ]
    },
    "alley": {
      "title": "Alley",
      "text": "In a narrow alley, something stirs between shallow puddles.",
      "combat": { "enemyId": "slime", "winNext": "win", "loseNext": "lose" }
    },
    "win": {
      "title": "Alley",
      "text": "It collapses. Your breathing is heavy—yet you live.",
      "effects": [
        { "type": "addGold", "value": 3 },
        { "type": "addExp", "value": 8 },
        { "type": "addItem", "itemId": "potion", "qty": 1 }
      ],
      "choices": [
  { "label": "Continue to Episode 2", "next": "to_ep2" }
      ]
      "to_ep2": {
  "title": "Continue",
  "text": "You leave the alley behind. Ahead, the city gate awaits.",
  "next_episode": "ep2"
      }
      
    },
    "lose": {
      "title": "Darkness",
      "text": "You fall. The world fades, but the story isn't over.",
      "effects": [
        { "type": "setHp", "value": 1 }
      ],
      "choices": [
        { "label": "Wake up", "next": "intro" }
      ]
    }
  }
}
